caproto/__init__.py
caproto/_array_backend.py
caproto/_backend.py
caproto/_broadcaster.py
caproto/_circuit.py
caproto/_commands.py
caproto/_constants.py
caproto/_data.py
caproto/_dbr.py
caproto/_headers.py
caproto/_log.py
caproto/_numpy_backend.py
caproto/_state.py
caproto/_status.py
caproto/_utils.py
caproto/_version.py
caproto/_windows_compat.py
caproto/asyncio/__init__.py
caproto/asyncio/client.py
caproto/asyncio/server.py
caproto/asyncio/utils.py
caproto/benchmarking/__init__.py
caproto/benchmarking/util.py
caproto/client/__init__.py
caproto/client/common.py
caproto/client/search_results.py
caproto/commandline/__init__.py
caproto/commandline/cli_print_formats.py
caproto/commandline/get.py
caproto/commandline/monitor.py
caproto/commandline/put.py
caproto/commandline/repeater.py
caproto/commandline/shark.py
caproto/curio/__init__.py
caproto/curio/server.py
caproto/curio/utils.py
caproto/docs/__init__.py
caproto/docs/utils.py
caproto/docs/templates/__init__.py
caproto/docs/templates/autosummary/__init__.py
caproto/docs/templates/autosummary/base.rst
caproto/docs/templates/autosummary/class.rst
caproto/docs/templates/autosummary/module.rst
caproto/examples/__init__.py
caproto/examples/asyncio_client_simple.py
caproto/examples/benchmark_connections.py
caproto/examples/thread_client_simple.py
caproto/examples/trio_server_simple.py
caproto/ioc_examples/__init__.py
caproto/ioc_examples/autosave.py
caproto/ioc_examples/big_image_noisy_neighbor.py
caproto/ioc_examples/chirp.py
caproto/ioc_examples/client_monitor_async.py
caproto/ioc_examples/custom_write.py
caproto/ioc_examples/decay.py
caproto/ioc_examples/enums.py
caproto/ioc_examples/fake_motor_record.py
caproto/ioc_examples/formula_ioc.py
caproto/ioc_examples/io_interrupt.py
caproto/ioc_examples/lakeshore.py
caproto/ioc_examples/macros.py
caproto/ioc_examples/mini_beamline.py
caproto/ioc_examples/mirror.py
caproto/ioc_examples/no_pvproperty.py
caproto/ioc_examples/random_walk.py
caproto/ioc_examples/records.py
caproto-1.3.0.dist-info/licenses/LICENSE
caproto-1.3.0.dist-info/METADATA
caproto-1.3.0.dist-info/WHEEL
caproto-1.3.0.dist-info/entry_points.txt
caproto-1.3.0.dist-info/top_level.txt
caproto-1.3.0.dist-info/RECORD
