Metadata-Version: 2.4
Name: caproto
Version: 1.3.0
Summary: a sans-I/O implementation of the EPICS Channel Access protocol
Author: Caproto Contributors
Classifier: Development Status :: 3 - Alpha
Classifier: Intended Audience :: Science/Research
Classifier: Programming Language :: Python
Classifier: Programming Language :: Python :: 3
Classifier: Programming Language :: Python :: 3.8
Classifier: Programming Language :: Python :: 3.9
Classifier: Programming Language :: Python :: 3.10
Classifier: Topic :: Scientific/Engineering :: Visualization
Classifier: License :: OSI Approved :: BSD License
Requires-Python: >=3.8
License-File: LICENSE
Provides-Extra: standard
Requires-Dist: netifaces; extra == "standard"
Requires-Dist: numpy; extra == "standard"
Requires-Dist: dpkt; extra == "standard"
Provides-Extra: async
Requires-Dist: curio>=1.2; extra == "async"
Requires-Dist: trio>=0.12.1; extra == "async"
Provides-Extra: complete
Requires-Dist: curio>=1.2; extra == "complete"
Requires-Dist: dpkt; extra == "complete"
Requires-Dist: netifaces; extra == "complete"
Requires-Dist: numpy; extra == "complete"
Requires-Dist: trio>=0.12.1; extra == "complete"
Provides-Extra: test
Requires-Dist: codecov; extra == "test"
Requires-Dist: coverage; extra == "test"
Requires-Dist: curio; extra == "test"
Requires-Dist: curio>=1.2; extra == "test"
Requires-Dist: dpkt; extra == "test"
Requires-Dist: epics-pypdb; extra == "test"
Requires-Dist: netifaces; extra == "test"
Requires-Dist: numpy; extra == "test"
Requires-Dist: ophyd; extra == "test"
Requires-Dist: parsimonious; extra == "test"
Requires-Dist: pyepics>=3.4.2; extra == "test"
Requires-Dist: pytest; extra == "test"
Requires-Dist: pytest-rerunfailures; extra == "test"
Requires-Dist: pytest-timeout; extra == "test"
Requires-Dist: pytest-xdist; extra == "test"
Requires-Dist: trio>=0.18.0; extra == "test"
Requires-Dist: trio>=0.12.1; extra == "test"
Dynamic: author
Dynamic: classifier
Dynamic: license-file
Dynamic: provides-extra
Dynamic: requires-python
Dynamic: summary
